iwifi/__init__.py
iwifi/__main__.py
iwifi/settings.py
iwifi-0.1.0.dist-info/METADATA
iwifi-0.1.0.dist-info/WHEEL
iwifi-0.1.0.dist-info/entry_points.txt
iwifi-0.1.0.dist-info/top_level.txt
iwifi-0.1.0.dist-info/RECORD
