Metadata-Version: 2.1
Name: iwifi
Version: 0.1.0
Summary: UNKNOWN
Home-page: https://github.com/536/iwifi
Author: JiangHui
License: MIT
Platform: UNKNOWN
Classifier: Programming Language :: Python :: 3.6
Classifier: Programming Language :: Python :: 3.7
Classifier: Programming Language :: Python :: 3.8
Classifier: Programming Language :: Python :: 3.9
Classifier: License :: OSI Approved :: MIT License
Requires-Python: >=3.6
Requires-Dist: click
Requires-Dist: qrcode
